setup.py
openwhisk_docker_action/__init__.py
openwhisk_docker_action.egg-info/PKG-INFO
openwhisk_docker_action.egg-info/SOURCES.txt
openwhisk_docker_action.egg-info/dependency_links.txt
openwhisk_docker_action.egg-info/requires.txt
openwhisk_docker_action.egg-info/top_level.txt