Metadata-Version: 1.1
Name: openwhisk-docker-action
Version: 0.1.7
Summary: A class to make writing openwhisk docker actions easier to write in python
Home-page: https://github.com/kognate/openwhisk_docker_action
Author: Joshua B. Smith
Author-email: kognate@gmail.com
License: MIT
Platform: UNKNOWN
Classifier: Programming Language :: Python
Classifier: Programming Language :: Python :: 3.5
